dte_colombia/__init__.py
dte_colombia/api.py
dte_colombia/constants.py
dte_colombia/exceptions.py
dte_colombia/utils.py
dte_colombia/models/__init__.py
dte_colombia/models/documents/__init__.py
dte_colombia/models/utilities/__init__.py
dte_colombia/models/utilities/account.py
dte_colombia-0.0.1.dist-info/LICENSE
dte_colombia-0.0.1.dist-info/METADATA
dte_colombia-0.0.1.dist-info/WHEEL
dte_colombia-0.0.1.dist-info/top_level.txt
dte_colombia-0.0.1.dist-info/RECORD
